{
  "type": "betterend:infusion",
  "catalysts": {
    "east": [
      {
        "item": {
          "item": "minecraft:soul_sand"
        }
      },
      {
        "item": {
          "item": "minecraft:soul_soil"
        }
      }
    ],
    "north": {
      "item": {
        "item": "betterend:enchanted_petal"
      }
    },
    "north_east": {
      "item": {
        "item": "minecraft:lapis_lazuli"
      }
    },
    "north_west": {
      "item": {
        "item": "minecraft:lapis_lazuli"
      }
    },
    "south": [
      {
        "item": {
          "item": "minecraft:soul_sand"
        }
      },
      {
        "item": {
          "item": "minecraft:soul_soil"
        }
      }
    ],
    "south_east": {
      "item": {
        "item": "minecraft:lapis_lazuli"
      }
    },
    "south_west": {
      "item": {
        "item": "minecraft:lapis_lazuli"
      }
    },
    "west": [
      {
        "item": {
          "item": "minecraft:soul_sand"
        }
      },
      {
        "item": {
          "item": "minecraft:soul_soil"
        }
      }
    ]
  },
  "group": "enchantment",
  "input": {
    "item": {
      "item": "minecraft:book"
    }
  },
  "result": {
    "item": "minecraft:enchanted_book",
    "nbt": {
      "minecraft:stored_enchantments": {
        "levels": {
          "minecraft:soul_speed": 1
        }
      }
    }
  },
  "time": 300
}